easy_sqlite_lib-0.1.2.dist-info/licenses/LICENSE
easysqlite/__init__.py
easysqlite/db.py
easysqlite/exceptions.py
easy_sqlite_lib-0.1.2.dist-info/METADATA
easy_sqlite_lib-0.1.2.dist-info/WHEEL
easy_sqlite_lib-0.1.2.dist-info/top_level.txt
easy_sqlite_lib-0.1.2.dist-info/RECORD
