Metadata-Version: 2.4
Name: easy-sqlite-lib
Version: 0.1.2
Summary: A user-friendly Python wrapper for SQLite.
Home-page: https://github.com/SinghArindam/EasySQLite
Author: Arindam Singh
Author-email: Arindam Singh <aa7is789@gmail.com>
License: Apache License
Project-URL: Homepage, https://github.com/SinghArindam/EasySQLite
Project-URL: Bug Reports, https://github.com/SinghArindam/EasySQLite/issues
Project-URL: Source, https://github.com/SinghArindam/EasySQLite
Keywords: sqlite,sqlite3,database,wrapper,easy,simple,python
Classifier: Programming Language :: Python :: 3
Classifier: Programming Language :: Python :: 3.8
Classifier: Programming Language :: Python :: 3.9
Classifier: Programming Language :: Python :: 3.10
Classifier: Programming Language :: Python :: 3.11
Classifier: License :: OSI Approved :: Apache Software License
Classifier: Operating System :: OS Independent
Classifier: Intended Audience :: Developers
Classifier: Topic :: Database
Classifier: Topic :: Software Development :: Libraries :: Python Modules
Classifier: Development Status :: 4 - Beta
Requires-Python: >=3.8
License-File: LICENSE
Provides-Extra: dev
Requires-Dist: build>=1.2.2.post1; extra == "dev"
Requires-Dist: pytest>=8.3.5; extra == "dev"
Requires-Dist: twine>=6.1.0; extra == "dev"
Dynamic: author
Dynamic: home-page
Dynamic: license-file
Dynamic: requires-python
